colorcycle/__init__.py
colorcycle/colorParser.py
colorcycle/color_convert.py
colorcycle/random_color.py
colorcycle-1.1.0.dist-info/LICENSE
colorcycle-1.1.0.dist-info/METADATA
colorcycle-1.1.0.dist-info/WHEEL
colorcycle-1.1.0.dist-info/top_level.txt
colorcycle-1.1.0.dist-info/RECORD
