Metadata-Version: 2.1
Name: colorcycle
Version: 1.1.0
Summary: ColorCycle is a Python package that helps developers easily convert color formats between Hex, RGB, and HSL. This tool is ideal for designers and developers working on color management for websites, applications, and graphical projects. Simply provide a color in any of the supported formats, and ColorCycle will convert it into the others.
Home-page: https://github.com/krishnatadi/colorcycle-python
Author: Krishna Tadi
Author-email: 
License: MIT
Project-URL: Documentation, https://github.com/krishnatadi/colorcycle-python#readme
Project-URL: Source, https://github.com/krishnatadi/colorcycle-python
Project-URL: Issue Tracker, https://github.com/krishnatadi/colorcycle-python/issues
Keywords: "color","color conversion","hex to rgb","rgb to hex","hex to hsl","rgb to hsl","hsl to rgb","hsl to hex","color parser","random color","web development","design","javascript","css colors","hex color","rgb color","hsl color","colorcycle","frontend tools","color utilities","color manipulation","color names","color library","web design","frontend development"
Classifier: Programming Language :: Python
Classifier: License :: OSI Approved :: MIT License
Classifier: Operating System :: OS Independent
Classifier: Intended Audience :: Developers
Classifier: Development Status :: 5 - Production/Stable
Classifier: Environment :: Console
Requires-Python: >=3.6
License-File: LICENSE
